langchain_gel/__init__.py
langchain_gel/vectorstore.py
langchain_gel-1.0.1.dist-info/METADATA
langchain_gel-1.0.1.dist-info/WHEEL
langchain_gel-1.0.1.dist-info/entry_points.txt
langchain_gel-1.0.1.dist-info/licenses/LICENSE
langchain_gel-1.0.1.dist-info/RECORD
