Metadata-Version: 2.4
Name: langchain-gel
Version: 1.0.1
Summary: Gel integration package for the LangChain framework
Author-email: anbuzin <andrey@geldata.com>
License-File: LICENSE
Requires-Python: >=3.9
Requires-Dist: gel>=3.0.1
Requires-Dist: jinja2>=3.1.4
Requires-Dist: langchain-core>=0.3.22
